README.md
setup.py
VAE_G2P/__init__.py
VAE_G2P/basic_g2p.py
VAE_G2P/cvae_model.py
VAE_G2P/data.py
VAE_G2P/data_wrapper.py
VAE_G2P/networks.py
VAE_G2P/optim.py
VAE_G2P/vae_g2p.py
VAE_G2P.egg-info/PKG-INFO
VAE_G2P.egg-info/SOURCES.txt
VAE_G2P.egg-info/dependency_links.txt
VAE_G2P.egg-info/requires.txt
VAE_G2P.egg-info/top_level.txt