Metadata-Version: 2.1
Name: VAE-G2P
Version: 0.0.2
Summary: A fully generative probability model that maps gene-based knowledge directly to disease symptoms, including their reported frequencies.
Home-page: https://github.com/daverblair/VAE_G2P
Author: David Blair
Author-email: david.blair@ucsf.edu
Classifier: Programming Language :: Python :: 3
Classifier: License :: OSI Approved :: MIT License
Classifier: Operating System :: OS Independent
